{
  "topic": "riemannian-geometry",
  "title": "Riemannian geometry",
  "page": "riemannian-geometry.html",
  "concepts": [
    {
      "id": "riemannian-metrics",
      "title": "Riemannian metrics",
      "anchor": "metric",
      "prereqs": [
        "smooth-manifold-definition",
        "tangent-space-manifolds"
      ],
      "blurb": "A smoothly varying inner product on tangent spaces defines length, angle, and volume."
    },
    {
      "id": "levi-civita-connection",
      "title": "Levi-Civita connection and geodesics",
      "anchor": "geodesics",
      "prereqs": [
        "riemannian-metrics"
      ],
      "blurb": "The unique torsion-free metric connection defines covariant differentiation and geodesic equations."
    },
    {
      "id": "riemann-curvature-tensor",
      "title": "Curvature tensor and comparison",
      "anchor": "comparison",
      "prereqs": [
        "levi-civita-connection"
      ],
      "blurb": "Sectional curvature controls topology and global metric behavior through comparison theorems."
    },
    {
      "id": "ricci-curvature",
      "title": "Ricci curvature and Einstein manifolds",
      "anchor": "ricci",
      "prereqs": [
        "riemann-curvature-tensor"
      ],
      "blurb": "The trace of the Riemann tensor measures average sectional curvature, governs geodesic-ball volumes, and drives Einstein's equations."
    },
    {
      "id": "volume-form-rg",
      "title": "Riemannian volume form and divergence",
      "anchor": "volume",
      "prereqs": [
        "riemannian-metrics",
        "forms-and-wedge"
      ],
      "blurb": "The metric produces a canonical volume form \\sqrt{\\det g}\\,dx^1\\wedge\\cdots\\wedge dx^n, giving integration, divergence, and the Laplace-Beltrami operator on (M,g)."
    }
  ]
}
